ctk_cli/__init__.py
ctk_cli/argument_parser.py
ctk_cli/execution.py
ctk_cli/module.py
ctk_cli/test.py
ctk_cli-1.5.dist-info/DESCRIPTION.rst
ctk_cli-1.5.dist-info/METADATA
ctk_cli-1.5.dist-info/RECORD
ctk_cli-1.5.dist-info/WHEEL
ctk_cli-1.5.dist-info/metadata.json
ctk_cli-1.5.dist-info/top_level.txt
