Metadata-Version: 1.1
Name: ctk-cli
Version: 1.5
Summary: Python interface for inspecting and running CLI modules (as defined by CommonTK)
Home-page: https://github.com/commontk/ctk-cli
Author: Hans Meine
Author-email: hans_meine@gmx.net
License: Apache 2.0
Keywords: CTK CLI Slicer host plugin module execution model XML
Platform: UNKNOWN
Classifier: Development Status :: 5 - Production/Stable
Classifier: Environment :: Web Environment
Classifier: License :: OSI Approved :: Apache Software License
Classifier: Operating System :: OS Independent
Classifier: Programming Language :: Python :: 2
Classifier: Programming Language :: Python :: 3
